{
  "id": "release-1765079020915-efdalryrh",
  "state": "failed",
  "type": "release",
  "startedAt": "2025-12-07T03:43:40.915Z",
  "completedStages": [],
  "failedStages": [
    "analysis"
  ],
  "context": {
    "analysisError": "Unexpected token '>', \"\n> designer\"... is not valid JSON",
    "lastFailedStage": "analysis"
  },
  "metadata": {
    "version": "pending",
    "trigger": "manual",
    "packages": []
  },
  "updatedAt": "2025-12-07T03:43:47.472Z",
  "completedAt": "2025-12-07T03:43:47.472Z"
}