{
  "id": "release-1764562164924-wy7uuxbme",
  "state": "failed",
  "type": "release",
  "startedAt": "2025-12-01T04:09:24.931Z",
  "completedStages": [],
  "failedStages": [
    "analysis"
  ],
  "context": {
    "analysisError": "Unexpected token '>', \"\n> designer\"... is not valid JSON",
    "lastFailedStage": "analysis"
  },
  "metadata": {
    "version": "pending",
    "trigger": "manual",
    "packages": []
  },
  "updatedAt": "2025-12-01T04:09:29.478Z",
  "completedAt": "2025-12-01T04:09:29.478Z"
}