{
  "id": "release-1764449459585-nzlhel7cx",
  "state": "failed",
  "type": "release",
  "startedAt": "2025-11-29T20:50:59.585Z",
  "completedStages": [],
  "failedStages": [
    "analysis"
  ],
  "context": {
    "analysisError": "Unexpected token '>', \"\n> designer\"... is not valid JSON",
    "lastFailedStage": "analysis"
  },
  "metadata": {
    "version": "pending",
    "trigger": "manual",
    "packages": []
  },
  "updatedAt": "2025-11-29T20:51:01.087Z",
  "completedAt": "2025-11-29T20:51:01.087Z"
}