{
  "id": "release-1764548180418-p9rk9ahsk",
  "state": "failed",
  "type": "release",
  "startedAt": "2025-12-01T00:16:20.418Z",
  "completedStages": [],
  "failedStages": [
    "analysis"
  ],
  "context": {
    "analysisError": "Unexpected token '>', \"\n> designer\"... is not valid JSON",
    "lastFailedStage": "analysis"
  },
  "metadata": {
    "version": "pending",
    "trigger": "manual",
    "packages": []
  },
  "updatedAt": "2025-12-01T00:16:24.164Z",
  "completedAt": "2025-12-01T00:16:24.164Z"
}