{
  "id": "1761763389-spec-completion",
  "type": "spec-completion",
  "source": "/Users/3fn/Documents/Work Projects/Kiro/DesignerPunk-v2/.kiro/specs/afternoon-to-dusk-rename/completion/task-1-2-completion.md",
  "triggeredAt": "2025-10-29T18:43:09.3NZ",
  "triggeredBy": "hook-system",
  "git": {
    "commit": "694541912896aeac77593430af77bbb874a0becb",
    "branch": "main",
    "message": "Audit: Complete README token count audit and corrections"
  },
  "workflow": {
    "hookType": "auto",
    "projectRoot": "/Users/3fn/Documents/Work Projects/Kiro/DesignerPunk-v2"
  },
  "status": "processed",
  "processedAt": "2025-10-29T18:43:10.068Z",
  "releaseSignal": {
    "type": "major",
    "trigger": "spec-completion",
    "confidence": 0.95,
    "evidence": [
      "Spec completion detected",
      "Found 117 new features",
      "Found 10 breaking changes",
      "Found 194 improvements"
    ],
    "affectedPackages": [
      "@designerpunk/tokens",
      "@designerpunk/build-system"
    ],
    "timestamp": "2025-10-29T18:43:10.068Z",
    "source": ".kiro/specs/afternoon-to-dusk-rename"
  }
}