{
  "id": "1764100061-spec-completion",
  "type": "spec-completion",
  "source": ".kiro/specs/009-variant-attribute-standardization/completion/task-2-2-completion.md",
  "triggeredAt": "2025-11-25T19:47:42.3NZ",
  "triggeredBy": "hook-system",
  "git": {
    "commit": "f7d6347d59403d5472b81fee5e06bc68c1245c2d",
    "branch": "main",
    "message": "Task Complete: Task 3 Complete: Update ButtonCTA Documentation"
  },
  "workflow": {
    "hookType": "auto",
    "projectRoot": "/Users/3fn/Documents/Work Projects/Kiro/DesignerPunk-v2"
  },
  "status": "pending"
}
